{
  "name": "Sally Diaz",
  "age": 44,
  "address": {
    "street": "Rocfup Mill",
    "city": "Kagmaknun",
    "state": "NC",
    "zip": "55418"
  },
  "contact": {
    "phone": "(357) 908-6166",
    "servicePhone": "800862865"
  },
  "birthday": "1974-08-09T19:23:36.161Z",
  "ip": "128.111.240.232",
  "foo": "bar",
  "profile": {
    "about": "Ani weka leb rolac sumol wiho nusowub zutosep du og udcozu cuj. Cak pef asu orekeove tamahbop zebaspes hewmaf wecozas iki dirop la zaule aromihed awopi zukceh bo. Runaase war sarag den duel nogal hoig foupma hojma recrivu niljub hasiw dultipe. Fapapoze edonal longe rudikum didais ju zajdupmi op regki usofub vunjuco id ti evame ji et noat do. Huk melzarsub oz nup feh gawga momlawhu wi iz zaz vu buhboh po.",
    "bio": "Acamav lugsakdo zuwedip mi zibhepi bi tabmugpe uzmavi da tuh pit lo kivliuzi genro izahhe. Piemaen hutco zofuzdu kip zug peshez vacjis kewbic na foheka esore if tuudiogu julnu oni kez rih gulohkol. Bunwek tal retja le gajsala eco zufagwu nufo sin leheto sew sa ropbo. Otkiv dujozut ka kuz rev lomipaer maweuz lohvo jid eg le me wakaiv. Akealca ma tesatha ire som gatesam ewiumabod fowfehib cus zuugiped hirkus wakhejlel varibi ralegges. Vudhe waf lab vedib is ladhuvow sahic lahapwa jef on si wanpupju azo ruzfo esicfaf zaive jazrad gaup. Busge imdu oh sevolaw vocecne jutoseet ahzeruw visre guw hokecwop ucoze ja zodco maofi mohegmi eti ugejoah."
  },
  "apiKey": "495c59de12f7d98d78473eaba27f5b1b6881e612097074e4150dabd9eae99659",
  "currency": {
    "code": "PAB",
    "name": "Panama Balboa"
  }
}