{
  "name": "Jim Farmer",
  "age": 19,
  "address": {
    "street": "Ihha Highway",
    "city": "Zizurik",
    "state": "CT",
    "zip": "53674"
  },
  "contact": {
    "phone": "(319) 574-3142",
    "servicePhone": "800379577"
  },
  "birthday": "1962-11-08T20:46:56.596Z",
  "ip": "107.148.207.27",
  "foo": "bar",
  "profile": {
    "about": "Majotfup beruc ligamuf oznobed kutki jeci ziho uci olkerah ru petad ra. Baug wontifwim co tup vurinu gipi zoc igizaznat belno bo zelof fakwaodi pimatuvom lebirge ucmejdo. Hoipma fet binli losido gibo hej tinus mopocaoz raledecis tuf tankin hi bil. Vuwut tozzazjib voblultez nucrih kof sa sevalo johuig gu pih ifowu pumnaepi koovi ka senkevheh ajalokot zu. Isipopod zeruzto lolniawe degacho lok jo wut fonkufu uk lon gubit ipi pewika. Ohjemov retke gog nojosi pakpenek ravukziz bufmoglon mewod pecarjaj hip ud hez gep urvon etokho omuninti.",
    "bio": "Ifvav efuv ij sakwurja rewbi so po puka azi porepnet ajolohi lon ninjatki. Ze farib rebu up zobfana fuikahan muapehi du re bur be pipnuc ogenivoz zav natudhub. Wodwe pizcef evimofuz sajwobe fi ibo owbubi masop kitob dila soufuz ki sihe vussok."
  },
  "apiKey": "9d8daacadcafd88b3246fba87404d1775f11766ad281e8c6d480fd2fe27a2287",
  "currency": {
    "code": "AFN",
    "name": "Afghanistan Afghani"
  }
}