{
  "name": "Cody Wheeler",
  "age": 55,
  "address": {
    "street": "Zokava Road",
    "city": "Rociti",
    "state": "KY",
    "zip": "76719"
  },
  "contact": {
    "phone": "(436) 695-9262",
    "servicePhone": "800199561"
  },
  "birthday": "1989-01-23T11:05:37.530Z",
  "ip": "172.26.117.228",
  "foo": "bar",
  "profile": {
    "about": "Ulruboke devi webiif ewpad ra iju ehu efbizbu empebpa wouwfut na goraz mewcoh vihzeb ab jor la sih. Fuwaggo cuskocin dasteji uvimacuf ow ez az efoiv limjuoc buewumu arkudum ifwi wiv zus. Bizcegpo wek wol zefda fupsubmuk kugner duhisti cizawcik zipzeowi higam ep miflurez anekuela imo idikog ru afu mu.",
    "bio": "Av sim edhomo ez zefadzu sadowu no kojecca mizmu bi saawvup juno. Sekbor bebe zo eksu babdo paotorus waafdo gewubu kekec cauji bitewe rob kortagpat bi povur ormo wewudaw majegewe. Ifsu lumtop wotizkaw sijem wus lit si belene wi pis zabuc ek woorucur ewo tun havpebve icicijzon narak. Puzis vofmos nak samkebzu wupi zew kev rajeheim ikeeb reikoul gusip hegsif secilved mo ceheazo."
  },
  "apiKey": "c8fd38cfabd874e7b8bcca646729219813ec5f5f643ef27e5a5288bc8be47103",
  "currency": {
    "code": "KZT",
    "name": "Kazakhstan Tenge"
  }
}