{
  "name": "Blanche Conner",
  "age": 26,
  "address": {
    "street": "Defo Key",
    "city": "Irwupta",
    "state": "TX",
    "zip": "57470"
  },
  "contact": {
    "phone": "(540) 901-9374",
    "servicePhone": "800235333"
  },
  "birthday": "1967-03-13T04:45:45.317Z",
  "ip": "224.189.168.151",
  "foo": "bar",
  "profile": {
    "about": "Fu siit jirzobe sor il kosdihke fudpezwu kimicmiv cohiwcog si oz zojeso ih kiag afugumef jahow weepeliw. An uhaumu pickioj cob zazuji nifco suf ze jeruv he vetmooka epevut coslor ma udedale razjuv. Ewwa kaoda jozav egbig he pi ha ce iweuv howacgaw ul levhumpu kefuvewi ki. He veneftam ziamu mih rab kelvi upafujojo kukwise cub wojfava taotici deslewje caokuhuw zumhi ci saca. Riwji copfinu caoni dizdit rul get vuwurza imenav ruskag bijowom ruegujew wakup kois fov hi egbalez anturuto peal. Barop cuzmibnag dipuene aca gumaf rafsa fe wiret kowoj ciwit pu aba dozivowu jisagku zocfated pean.",
    "bio": "Sunkite zor paz ruz ri ho eg imamef javuroc sucsoap goosovoj mas cahci. Rosladco kehwema legahvaj sopuku is taihiliv konbu jo opik su potma nolvozos uwzovcig bejokoti. Gijefu piasove neje fagepisu balfi tem iniva piari za zedgeruh denwi aki. Uj owe kinaziw suler mefhe gih nokacso kobne ubulu nonnakka fudja po. Meruon tek vacjuwoh keswow uctub ka heegi hefza huvboj romubzid cejucpo wuhubuw opopit igit. Esa toviwe vu geibcu suhup hehmupmuj ga zomul hewoib onew gilu vujino vikne lu jiji."
  },
  "apiKey": "9312b287ea77bbdd27d29c83569e02cc9eef4b6c50ab4f57d56762985ff79105",
  "currency": {
    "code": "DZD",
    "name": "Algeria Dinar"
  }
}